simple_coverage/__init__.py
simple_coverage/analyze.py
simple_coverage/clean.py
simple_coverage/coverage.py
simple_coverage/output.py
simple_coverage/report.py
simple_coverage-0.3.2.dist-info/LICENSE
simple_coverage-0.3.2.dist-info/METADATA
simple_coverage-0.3.2.dist-info/WHEEL
simple_coverage-0.3.2.dist-info/top_level.txt
simple_coverage-0.3.2.dist-info/RECORD
