Metadata-Version: 2.1
Name: simple-coverage
Version: 0.3.2
Summary: Simple Coverage measurements for Python
Home-page: https://github.com/nikolim/simple-coverage
Author: Nikolai Limbrunner
Author-email: nikolai.limbrunner@gmail.com
License: UNKNOWN
Platform: UNKNOWN
Requires-Python: >=3.6
License-File: LICENSE
Requires-Dist: termcolor
